aiobbox/__init__.py
aiobbox/client.py
aiobbox/exceptions.py
aiobbox/models.py
aiobbox/py.typed
aiobbox-0.3.1.dist-info/WHEEL
aiobbox-0.3.1.dist-info/METADATA
aiobbox-0.3.1.dist-info/RECORD
