Metadata-Version: 2.4
Name: aiobbox
Version: 0.3.1
Summary: Async Python API wrapper for Bouygues Telecom routers
Keywords: bbox,bouygues,router,api,async
Author: Sweenu
Author-email: Sweenu <contact@sweenu.xyz>
License-Expression: Apache-2.0
Classifier: Development Status :: 3 - Alpha
Classifier: Intended Audience :: Developers
Classifier: Operating System :: OS Independent
Classifier: Programming Language :: Python :: 3
Classifier: Programming Language :: Python :: 3.13
Classifier: Programming Language :: Python :: 3.14
Classifier: Topic :: Home Automation
Classifier: Topic :: Software Development :: Libraries :: Python Modules
Requires-Dist: aiohttp>=3.9.0
Requires-Dist: pydantic>=2.0.0
Requires-Python: >=3.13
Project-URL: Documentation, https://github.com/sweenu/aiobbox#readme
Project-URL: Homepage, https://github.com/sweenu/aiobbox
Project-URL: Issues, https://github.com/sweenu/aiobbox/issues
Project-URL: Repository, https://github.com/sweenu/aiobbox
